rudradb/__init__.py
rudradb/rudradb.cp312-win_amd64.pyd
rudradb_opin-1.0.0.dist-info/METADATA
rudradb_opin-1.0.0.dist-info/WHEEL
rudradb_opin-1.0.0.dist-info/licenses/LICENSE
rudradb_opin-1.0.0.dist-info/RECORD
