Metadata-Version: 2.4
Name: rudradb-opin
Version: 1.0.0
Classifier: Development Status :: 5 - Production/Stable
Classifier: Intended Audience :: Developers
Classifier: Intended Audience :: Education
Classifier: Intended Audience :: Science/Research
Classifier: License :: OSI Approved :: MIT License
Classifier: Operating System :: OS Independent
Classifier: Programming Language :: Python :: 3
Classifier: Programming Language :: Python :: 3.8
Classifier: Programming Language :: Python :: 3.9
Classifier: Programming Language :: Python :: 3.10
Classifier: Programming Language :: Python :: 3.11
Classifier: Programming Language :: Python :: 3.12
Classifier: Programming Language :: Rust
Classifier: Topic :: Database
Classifier: Topic :: Scientific/Engineering :: Artificial Intelligence
Classifier: Topic :: Scientific/Engineering :: Information Analysis
Classifier: Topic :: Software Development :: Libraries :: Python Modules
Classifier: Topic :: Education
Classifier: Typing :: Typed
Requires-Dist: numpy>=1.20.0
Requires-Dist: pytest>=6.0 ; extra == 'dev'
Requires-Dist: pytest-cov ; extra == 'dev'
Requires-Dist: black ; extra == 'dev'
Requires-Dist: ruff ; extra == 'dev'
Requires-Dist: mypy ; extra == 'dev'
Requires-Dist: build ; extra == 'dev'
Requires-Dist: twine ; extra == 'dev'
Requires-Dist: openai>=0.27.0 ; extra == 'examples'
Requires-Dist: sentence-transformers>=2.2.0 ; extra == 'examples'
Requires-Dist: transformers>=4.20.0 ; extra == 'examples'
Requires-Dist: torch>=1.12.0 ; extra == 'examples'
Requires-Dist: scikit-learn>=1.1.0 ; extra == 'examples'
Requires-Dist: matplotlib>=3.5.0 ; extra == 'examples'
Requires-Dist: pandas>=1.5.0 ; extra == 'examples'
Requires-Dist: jupyter>=1.0.0 ; extra == 'examples'
Requires-Dist: rudradb-opin[dev,examples] ; extra == 'all'
Provides-Extra: dev
Provides-Extra: examples
Provides-Extra: all
License-File: LICENSE
Summary: RudraDB-Opin: Free relationship-aware vector database for learning and tutorials (100 vectors, 500 relationships)
Keywords: vector,database,relationships,ai,ml,machine-learning,vector-search,similarity-search,embeddings,free,learning,tutorial,education,rag,retrieval-augmented-generation,semantic-search,relationship-aware,multi-hop,graph
Home-Page: https://rudradb.com
Author-email: Mahesh Vaikri <mahesh@rudradb.com>
Maintainer-email: RudraDB Team <support@rudradb.com>
Requires-Python: >=3.8
Project-URL: Homepage, https://rudradb.com
Project-URL: Documentation, https://www.rudradb.com/docs.html
Project-URL: Upgrade to Full RudraDB, https://rudradb.com/upgrade.html
